README.md
setup.cfg
setup.py
area_1.egg-info/PKG-INFO
area_1.egg-info/SOURCES.txt
area_1.egg-info/dependency_links.txt
area_1.egg-info/requires.txt
area_1.egg-info/top_level.txt
src/__init__.py
src/area_determ.py
src/loger.py